rtl/special_case.v
module special_case(
    input  [31:0] in,

    output is_zero,
    output is_inf,
    output is_nan,
    output is_subnormal,
    output is_normal
);

wire [7:0] exp;
wire [22:0] frac;

assign exp  = in[30:23];
assign frac = in[22:0];

assign is_zero      = (exp == 8'h00) && (frac == 23'h000000);
assign is_inf       = (exp == 8'hFF) && (frac == 23'h000000);
assign is_nan       = (exp == 8'hFF) && (frac != 23'h000000);
assign is_subnormal = (exp == 8'h00) && (frac != 23'h000000);
assign is_normal    = (exp != 8'h00) && (exp != 8'hFF);

endmodule

rtl/unpack.v
module unpack(
input [31:0] in,
output sign,
output [7:0] exp,
output [23:0] mant
);
assign sign = in[31];
assign exp = in[30:23];

//hitten bit handling 
assign mant = (exp==8'd0)?
{1'b0, in[22:0]} : //Subnormal number
{1'b1, in[22:0]}; //Normal number 
endmodule

rtl/fp_div.v
module fp_div(
    input  [31:0] a,
    input  [31:0] b,

    output reg [31:0] result
);

//--------------------------------------------------
// Unpack
//--------------------------------------------------

wire sign_a;
wire sign_b;

wire [7:0] exp_a;
wire [7:0] exp_b;

wire [23:0] mant_a;
wire [23:0] mant_b;

unpack ua(
    .in(a),
    .sign(sign_a),
    .exp(exp_a),
    .mant(mant_a)
);

unpack ub(
    .in(b),
    .sign(sign_b),
    .exp(exp_b),
    .mant(mant_b)
);

//--------------------------------------------------
// Special Case Detection
//--------------------------------------------------

wire is_zero_a;
wire is_inf_a;
wire is_nan_a;
wire is_subnormal_a;
wire is_normal_a;

wire is_zero_b;
wire is_inf_b;
wire is_nan_b;
wire is_subnormal_b;
wire is_normal_b;

special_case sca(
    .in(a),
    .is_zero(is_zero_a),
    .is_inf(is_inf_a),
    .is_nan(is_nan_a),
    .is_subnormal(is_subnormal_a),
    .is_normal(is_normal_a)
);

special_case scb(
    .in(b),
    .is_zero(is_zero_b),
    .is_inf(is_inf_b),
    .is_nan(is_nan_b),
    .is_subnormal(is_subnormal_b),
    .is_normal(is_normal_b)
);

//--------------------------------------------------
// Divider Core
//--------------------------------------------------

wire sign_result;

assign sign_result = sign_a ^ sign_b;

wire [47:0] dividend;

assign dividend = {mant_a,24'd0};

wire [23:0] quotient;

assign quotient = dividend / mant_b;

reg [7:0] exp_result;

always @(*) begin

    exp_result = exp_a - exp_b + 8'd127;

    //--------------------------------------------------
    // IEEE-754 Special Cases
    //--------------------------------------------------

    // NaN
    if(is_nan_a || is_nan_b)
        result = 32'h7FC00000;

    // 0 / 0 = NaN
    else if(is_zero_a && is_zero_b)
        result = 32'h7FC00000;

    // Inf / Inf = NaN
    else if(is_inf_a && is_inf_b)
        result = 32'h7FC00000;

    // Divide by zero -> Infinity
    else if(is_zero_b)
        result = {
            sign_result,
            8'hFF,
            23'd0
        };

    // 0 / X = 0
    else if(is_zero_a)
        result = {
            sign_result,
            8'd0,
            23'd0
        };

    // Inf / finite = Inf
    else if(is_inf_a)
        result = {
            sign_result,
            8'hFF,
            23'd0
        };

    // finite / Inf = 0
    else if(is_inf_b)
        result = {
            sign_result,
            8'd0,
            23'd0
        };

    //--------------------------------------------------
    // Normal Division
    //--------------------------------------------------

    else begin

        result = {
            sign_result,
            exp_result,
            quotient[22:0]
        };

    end

end

endmodule

tb/fp_div_tb.v
`timescale 1ns/1ps

module fp_div_tb;

reg [31:0] a;
reg [31:0] b;

wire [31:0] result;

fp_div uut(
    .a(a),
    .b(b),
    .result(result)
);

initial begin

    $dumpfile("fp_div.vcd");
    $dumpvars(0,fp_div_tb);

    // 8 / 2 = 4

    a = 32'h41000000;
    b = 32'h40000000;

    #20;

    $display("8/2 = %h",result);



    // -8 / 2 = -4

    a = 32'hC1000000;
    b = 32'h40000000;

    #20;

    $display("-8/2 = %h",result);


// 0 / 5 = 0
a = 32'h00000000;
b = 32'h40A00000;
#20;
$display("0/5 = %h",result);

// 5 / 0 = Inf
a = 32'h40A00000;
b = 32'h00000000;
#20;
$display("5/0 = %h",result);

// Inf / 2 = Inf
a = 32'h7F800000;
b = 32'h40000000;
#20;
$display("Inf/2 = %h",result);

// 2 / Inf = 0
a = 32'h40000000;
b = 32'h7F800000;
#20;
$display("2/Inf = %h",result);

// Inf / Inf = NaN
a = 32'h7F800000;
b = 32'h7F800000;
#20;
$display("Inf/Inf = %h",result);

// 0 / 0 = NaN
a = 32'h00000000;
b = 32'h00000000;
#20;
$display("0/0 = %h",result);

// NaN / 2 = NaN
a = 32'h7FC00000;
b = 32'h40000000;
#20;
$display("NaN/2 = %h",result);

    $finish;

end

endmodule

sim/fp_div.vcd
$date
	Thu Jun 25 12:59:17 2026
$end
$version
	Icarus Verilog
$end
$timescale
	1ps
$end
$scope module fp_div_tb $end
$var wire 32 ! result [31:0] $end
$var reg 32 " a [31:0] $end
$var reg 32 # b [31:0] $end
$scope module uut $end
$var wire 32 $ a [31:0] $end
$var wire 32 % b [31:0] $end
$var wire 1 & sign_result $end
$var wire 1 ' sign_b $end
$var wire 1 ( sign_a $end
$var wire 24 ) quotient [23:0] $end
$var wire 24 * mant_b [23:0] $end
$var wire 24 + mant_a [23:0] $end
$var wire 1 , is_zero_b $end
$var wire 1 - is_zero_a $end
$var wire 1 . is_subnormal_b $end
$var wire 1 / is_subnormal_a $end
$var wire 1 0 is_normal_b $end
$var wire 1 1 is_normal_a $end
$var wire 1 2 is_nan_b $end
$var wire 1 3 is_nan_a $end
$var wire 1 4 is_inf_b $end
$var wire 1 5 is_inf_a $end
$var wire 8 6 exp_b [7:0] $end
$var wire 8 7 exp_a [7:0] $end
$var wire 48 8 dividend [47:0] $end
$var reg 8 9 exp_result [7:0] $end
$var reg 32 : result [31:0] $end
$scope module sca $end
$var wire 32 ; in [31:0] $end
$var wire 1 5 is_inf $end
$var wire 1 3 is_nan $end
$var wire 1 1 is_normal $end
$var wire 1 / is_subnormal $end
$var wire 1 - is_zero $end
$var wire 23 < frac [22:0] $end
$var wire 8 = exp [7:0] $end
$upscope $end
$scope module scb $end
$var wire 32 > in [31:0] $end
$var wire 1 4 is_inf $end
$var wire 1 2 is_nan $end
$var wire 1 0 is_normal $end
$var wire 1 . is_subnormal $end
$var wire 1 , is_zero $end
$var wire 23 ? frac [22:0] $end
$var wire 8 @ exp [7:0] $end
$upscope $end
$scope module ua $end
$var wire 32 A in [31:0] $end
$var wire 1 ( sign $end
$var wire 24 B mant [23:0] $end
$var wire 8 C exp [7:0] $end
$upscope $end
$scope module ub $end
$var wire 32 D in [31:0] $end
$var wire 1 ' sign $end
$var wire 24 E mant [23:0] $end
$var wire 8 F exp [7:0] $end
$upscope $end
$upscope $end
$upscope $end
$enddefinitions $end
$comment Show the parameter values. $end
$dumpall
$end
#0
$dumpvars
b10000000 F
b100000000000000000000000 E
b1000000000000000000000000000000 D
b10000010 C
b100000000000000000000000 B
b1000001000000000000000000000000 A
b10000000 @
b0 ?
b1000000000000000000000000000000 >
b10000010 =
b0 <
b1000001000000000000000000000000 ;
b1000000100000000000000000000000 :
b10000001 9
b100000000000000000000000000000000000000000000000 8
b10000010 7
b10000000 6
05
04
03
02
11
10
0/
0.
0-
0,
b100000000000000000000000 +
b100000000000000000000000 *
b0 )
0(
0'
0&
b1000000000000000000000000000000 %
b1000001000000000000000000000000 $
b1000000000000000000000000000000 #
b1000001000000000000000000000000 "
b1000000100000000000000000000000 !
$end
#20000
b11000000100000000000000000000000 !
b11000000100000000000000000000000 :
1&
1(
b11000001000000000000000000000000 "
b11000001000000000000000000000000 $
b11000001000000000000000000000000 ;
b11000001000000000000000000000000 A
#40000
b101000000000000000000000 *
b101000000000000000000000 E
b0 8
1-
01
0&
b0 +
b0 B
b0 !
b0 :
b11111110 9
b10000001 @
b1000000000000000000000 ?
b10000001 6
b10000001 F
b0 =
0(
b0 7
b0 C
b1000000101000000000000000000000 #
b1000000101000000000000000000000 %
b1000000101000000000000000000000 >
b1000000101000000000000000000000 D
b0 "
b0 $
b0 ;
b0 A
#60000
bx )
b1111111100000000000000000000000 !
b1111111100000000000000000000000 :
b101000000000000000000000000000000000000000000000 8
00
1,
b0 *
b0 E
11
0-
b101000000000000000000000 +
b101000000000000000000000 B
b0 9
b0 @
b0 ?
b0 6
b0 F
b10000001 =
b1000000000000000000000 <
b10000001 7
b10000001 C
b0 #
b0 %
b0 >
b0 D
b1000000101000000000000000000000 "
b1000000101000000000000000000000 $
b1000000101000000000000000000000 ;
b1000000101000000000000000000000 A
#80000
b0 )
b100000000000000000000000000000000000000000000000 8
b100000000000000000000000 +
b100000000000000000000000 B
0,
10
b100000000000000000000000 *
b100000000000000000000000 E
01
15
b11111110 9
b10000000 @
b10000000 6
b10000000 F
b11111111 =
b0 <
b11111111 7
b11111111 C
b1000000000000000000000000000000 #
b1000000000000000000000000000000 %
b1000000000000000000000000000000 >
b1000000000000000000000000000000 D
b1111111100000000000000000000000 "
b1111111100000000000000000000000 $
b1111111100000000000000000000000 ;
b1111111100000000000000000000000 A
#100000
b0 !
b0 :
14
00
05
11
b0 9
b11111111 @
b11111111 6
b11111111 F
b10000000 =
b10000000 7
b10000000 C
b1111111100000000000000000000000 #
b1111111100000000000000000000000 %
b1111111100000000000000000000000 >
b1111111100000000000000000000000 D
b1000000000000000000000000000000 "
b1000000000000000000000000000000 $
b1000000000000000000000000000000 ;
b1000000000000000000000000000000 A
#120000
b1111111110000000000000000000000 !
b1111111110000000000000000000000 :
15
01
b1111111 9
b11111111 =
b11111111 7
b11111111 C
b1111111100000000000000000000000 "
b1111111100000000000000000000000 $
b1111111100000000000000000000000 ;
b1111111100000000000000000000000 A
#140000
bx )
b0 8
1,
04
b0 *
b0 E
1-
05
b0 +
b0 B
b0 @
b0 6
b0 F
b0 =
b0 7
b0 C
b0 #
b0 %
b0 >
b0 D
b0 "
b0 $
b0 ;
b0 A
#160000
b100000000000000000000000 )
b110000000000000000000000000000000000000000000000 8
0,
10
b100000000000000000000000 *
b100000000000000000000000 E
0-
13
b110000000000000000000000 +
b110000000000000000000000 B
b11111110 9
b10000000 @
b10000000 6
b10000000 F
b11111111 =
b10000000000000000000000 <
b11111111 7
b11111111 C
b1000000000000000000000000000000 #
b1000000000000000000000000000000 %
b1000000000000000000000000000000 >
b1000000000000000000000000000000 D
b1111111110000000000000000000000 "
b1111111110000000000000000000000 $
b1111111110000000000000000000000 ;
b1111111110000000000000000000000 A
